[
    {
        "name":"National Pension Scheme",
        "description":"Let's secure your future! Drop your queries and we will get back to you!"
    },
    {
        "name":"Gold Loan",
        "description":"Turn your gold into cash! Drop your queries and we will get back to you!"
    },
    {
        "name":"Home Loan",
        "description":"Plan your dream home with us! Drop your queries and we will get back to you!"
    },
    {
        "name":"Car Loan",
        "description":"Owning a car is no more a dream! Finanziell is here to help you. Drop your queries here and we will get back to you!"
    },
    {
        "name":"Education Loan",
        "description":"We promise to make your college affordable! Drop your queries and we will get back to you!"
    },
    {
        "name":"Mutual Funds",
        "description":"Scared to invest? Invest with us! Drop your queries and we will get back to you!"
    }
]